mapping_length_analysis/__main__.py
mapping_length_analysis-0.0.2.dist-info/METADATA
mapping_length_analysis-0.0.2.dist-info/WHEEL
mapping_length_analysis-0.0.2.dist-info/entry_points.txt
mapping_length_analysis-0.0.2.dist-info/top_level.txt
mapping_length_analysis-0.0.2.dist-info/RECORD
