Metadata-Version: 2.1
Name: mapping-length-analysis
Version: 0.0.2
Summary: Analyse number of raw and mapped reads by length
Home-page: https://github.com/Delayed-Gitification/mapping_length_analysis.git
Author: Oscar Wilkins
Author-email: oscar.wilkins@crick.ac.uk
License: MIT
Platform: UNKNOWN
Classifier: License :: OSI Approved :: MIT License
Classifier: Programming Language :: Python :: 3
Classifier: Programming Language :: Python :: 3.7
Requires-Dist: pandas
Requires-Dist: dnaio
Requires-Dist: pysam
